booltest/__init__.py
booltest/battery.py
booltest/booltest_json.py
booltest/booltest_main.py
booltest/common.py
booltest/crypto_util.py
booltest/egenerator.py
booltest/gen-aes.py
booltest/input_obj.py
booltest/jsonenc.py
booltest/misc.py
booltest/pvals.py
booltest/randverif.py
booltest/runner.py
booltest/testbatteries.py
booltest/testbed.py
booltest/testjobs.py
booltest/testjobsbase.py
booltest/testjobsproc.py
booltest/timer.py
booltest/assets/__init__.py
booltest/assets/pval_db.json
booltest/tests/__init__.py
booltest/tests/test_booltest.py
booltest/tests/test_common.py
booltest/tests/test_eval.py
booltest/tests/test_misc.py
booltest/tests/data/.gitignore
booltest/tests/data/randc_seed1_prob16_and_x0_x42.data
booltest/tests/data/randc_seed1_prob16_x0.data
booltest/tests/data/randc_seed1_prob1_and_x0_x42.data
booltest/tests/data/randc_seed1_prob1_and_x0_x42_x100.data
booltest/tests/data/randc_seed1_prob1_and_x0_x42_x100_x127.data
booltest/tests/data/randc_seed1_prob1_x0.data
booltest/tests/data/randc_seed1_prob1_xor_x0_x42.data
booltest/tests/data/randc_seed1_prob1_xor_x0_x42_x100.data
booltest_tools/__init__.py
booltest_tools/aesproc.py
booltest_tools/aespval.py
booltest_tools/aessize.py
booltest_tools/camellia_testvectors.py
booltest_tools/csvgen.py
booltest_tools/list2csv.py
booltest_tools/pval_ext.py
booltest_tools/round_reduce.py
booltest_tools/rttfetch.py
booltest_tools/simple_graph.py
booltest_tools/testmatrix.py
booltest-0.6.0.dist-info/LICENSE
booltest-0.6.0.dist-info/METADATA
booltest-0.6.0.dist-info/WHEEL
booltest-0.6.0.dist-info/entry_points.txt
booltest-0.6.0.dist-info/top_level.txt
booltest-0.6.0.dist-info/RECORD
