Metadata-Version: 2.1
Name: booltest
Version: 0.6.0
Summary: BoolTest: Polynomial randomness tester
Home-page: https://github.com/ph4r05/polynomial-distinguishers
Author: Dusan Klinec
Author-email: dusan.klinec@gmail.com
License: MIT
Platform: UNKNOWN
Classifier: Development Status :: 3 - Alpha
Classifier: Intended Audience :: Developers
Classifier: Programming Language :: Python
Classifier: Programming Language :: Python :: 2
Classifier: Programming Language :: Python :: 2.6
Classifier: Programming Language :: Python :: 2.7
Classifier: Programming Language :: Python :: 3
Classifier: Programming Language :: Python :: 3.3
Classifier: Programming Language :: Python :: 3.4
Classifier: Programming Language :: Python :: 3.5
Classifier: Topic :: Security
Requires-Dist: pycryptodome
Requires-Dist: bitarray-ph4 (>=1.2.3)
Requires-Dist: scipy
Requires-Dist: ufx
Requires-Dist: repoze.lru
Requires-Dist: setuptools (>=1.0)
Requires-Dist: six
Requires-Dist: future
Requires-Dist: requests
Requires-Dist: coloredlogs
Requires-Dist: psutil
Requires-Dist: pid (>=2.0.1)
Requires-Dist: py-cpuinfo
Requires-Dist: jsonpath-ng
Requires-Dist: shellescape
Requires-Dist: sarge (>=0.1.4)
Provides-Extra: dev
Requires-Dist: nose ; extra == 'dev'
Requires-Dist: pep8 ; extra == 'dev'
Requires-Dist: tox ; extra == 'dev'
Requires-Dist: pypandoc ; extra == 'dev'
Provides-Extra: docs
Requires-Dist: Sphinx (>=1.0) ; extra == 'docs'
Requires-Dist: sphinx-rtd-theme ; extra == 'docs'
Requires-Dist: sphinxcontrib-programoutput ; extra == 'docs'
Provides-Extra: impl
Requires-Dist: bitstring ; extra == 'impl'
Requires-Dist: numpy ; extra == 'impl'
